{
  "meta": {
    "date": "2026-06-19",
    "generated_at": "2026-06-19T20:51:59Z"
  },
  "signals": [
    "High funding rates: XMR, SIREN, BEAT \u2014 longs overcrowded, reversal risk",
    "Negative funding: H, SAHARA, VVV \u2014 shorts paying, potential squeeze",
    "Rising OI (6h): XAUT, RIVER, M \u2014 fresh positions building",
    "Top gainers today: ACT +21.64%, BLESS +18.82%, ORDI +17.1%",
    "Highest volume: BTC, ETH, XAUT"
  ],
  "coins": {
    "SOLUSD": {
      "name": "SOL",
      "symbol": "SOLUSD",
      "price": 69.135,
      "oi_usd": 13273185.0,
      "oi_trend": "Falling",
      "oi_change_6h": -312954.0,
      "funding": {
        "rate": 1.0,
        "annualized": 1095.0,
        "sentiment": "Long Heavy"
      },
      "ls_ratio": null
    },
    "BNBUSD": {
      "name": "BNB",
      "symbol": "BNBUSD",
      "price": 581.86,
      "oi_usd": 550866.0,
      "oi_trend": "Rising",
      "oi_change_6h": 55028.0,
      "funding": {
        "rate": 5.1739,
        "annualized": 5665.4,
        "sentiment": "Long Heavy"
      },
      "ls_ratio": null
    },
    "XRPUSD": {
      "name": "XRP",
      "symbol": "XRPUSD",
      "price": 1.1327,
      "oi_usd": 2971877.0,
      "oi_trend": "Falling",
      "oi_change_6h": -33262.0,
      "funding": {
        "rate": 1.0,
        "annualized": 1095.0,
        "sentiment": "Long Heavy"
      },
      "ls_ratio": null
    },
    "ADAUSD": {
      "name": "ADA",
      "symbol": "ADAUSD",
      "price": 0.1617,
      "oi_usd": 465357.0,
      "oi_trend": "Falling",
      "oi_change_6h": -2890.0,
      "funding": {
        "rate": 1.0,
        "annualized": 1095.0,
        "sentiment": "Long Heavy"
      },
      "ls_ratio": null
    },
    "AVAXUSD": {
      "name": "AVAX",
      "symbol": "AVAXUSD",
      "price": 5.91,
      "oi_usd": 329619.0,
      "oi_trend": "Falling",
      "oi_change_6h": -88043.0,
      "funding": {
        "rate": 1.0,
        "annualized": 1095.0,
        "sentiment": "Long Heavy"
      },
      "ls_ratio": null
    },
    "DOTUSD": {
      "name": "DOT",
      "symbol": "DOTUSD",
      "price": 0.954,
      "oi_usd": 200256.0,
      "oi_trend": "Falling",
      "oi_change_6h": -3001.0,
      "funding": {
        "rate": 1.0,
        "annualized": 1095.0,
        "sentiment": "Long Heavy"
      },
      "ls_ratio": null
    },
    "LINKUSD": {
      "name": "LINK",
      "symbol": "LINKUSD",
      "price": 7.872,
      "oi_usd": 362641.0,
      "oi_trend": "Falling",
      "oi_change_6h": -648.0,
      "funding": {
        "rate": -1.7788,
        "annualized": -1947.8,
        "sentiment": "Short Heavy"
      },
      "ls_ratio": null
    },
    "ARBUSD": {
      "name": "ARB",
      "symbol": "ARBUSD",
      "price": 0.0829,
      "oi_usd": 53412.0,
      "oi_trend": "Rising",
      "oi_change_6h": 157.0,
      "funding": {
        "rate": 1.0,
        "annualized": 1095.0,
        "sentiment": "Long Heavy"
      },
      "ls_ratio": null
    },
    "OPUSD": {
      "name": "OP",
      "symbol": "OPUSD",
      "price": 0.1017,
      "oi_usd": 65604.0,
      "oi_trend": "Rising",
      "oi_change_6h": 240.0,
      "funding": {
        "rate": -12.8852,
        "annualized": -14109.3,
        "sentiment": "Short Heavy"
      },
      "ls_ratio": null
    },
    "INJUSD": {
      "name": "INJ",
      "symbol": "INJUSD",
      "price": 5.093,
      "oi_usd": 18465.0,
      "oi_trend": "Rising",
      "oi_change_6h": 214.0,
      "funding": {
        "rate": -1.5285,
        "annualized": -1673.7,
        "sentiment": "Short Heavy"
      },
      "ls_ratio": null
    },
    "APTUSD": {
      "name": "APT",
      "symbol": "APTUSD",
      "price": 0.629,
      "oi_usd": 16795.0,
      "oi_trend": "Rising",
      "oi_change_6h": 1.0,
      "funding": {
        "rate": -1.2484,
        "annualized": -1367.0,
        "sentiment": "Short Heavy"
      },
      "ls_ratio": null
    },
    "SUIUSD": {
      "name": "SUI",
      "symbol": "SUIUSD",
      "price": 0.7124,
      "oi_usd": 262225.0,
      "oi_trend": "Rising",
      "oi_change_6h": 4016.0,
      "funding": {
        "rate": 1.0,
        "annualized": 1095.0,
        "sentiment": "Long Heavy"
      },
      "ls_ratio": null
    },
    "DOGEUSD": {
      "name": "DOGE",
      "symbol": "DOGEUSD",
      "price": 0.0832,
      "oi_usd": 926931.0,
      "oi_trend": "Rising",
      "oi_change_6h": 18814.0,
      "funding": {
        "rate": 3.3137,
        "annualized": 3628.5,
        "sentiment": "Long Heavy"
      },
      "ls_ratio": null
    },
    "UNIUSD": {
      "name": "UNI",
      "symbol": "UNIUSD",
      "price": 3.031,
      "oi_usd": 146415.0,
      "oi_trend": "Falling",
      "oi_change_6h": -41983.0,
      "funding": {
        "rate": 5.024,
        "annualized": 5501.3,
        "sentiment": "Long Heavy"
      },
      "ls_ratio": null
    },
    "BTCUSD": {
      "name": "BTC",
      "symbol": "BTCUSD",
      "price": 63173.0,
      "oi_usd": 56060997.0,
      "oi_trend": "Falling",
      "oi_change_6h": -2848393.0,
      "funding": {
        "rate": 1.0,
        "annualized": 1095.0,
        "sentiment": "Long Heavy"
      },
      "ls_ratio": null
    },
    "ETHUSD": {
      "name": "ETH",
      "symbol": "ETHUSD",
      "price": 1705.85,
      "oi_usd": 33038313.0,
      "oi_trend": "Falling",
      "oi_change_6h": -2506279.0,
      "funding": {
        "rate": 0.0051,
        "annualized": 5.6,
        "sentiment": "Neutral"
      },
      "ls_ratio": null
    }
  },
  "oi_analysis": {
    "top_oi": [
      {
        "symbol": "BTCUSD",
        "name": "BTC",
        "oi_usd": 56060997.0,
        "oi_change_6h": -2848393.0,
        "price": 63173.0,
        "change_pct": 0.21
      },
      {
        "symbol": "ETHUSD",
        "name": "ETH",
        "oi_usd": 33038313.0,
        "oi_change_6h": -2506279.0,
        "price": 1705.85,
        "change_pct": -0.24
      },
      {
        "symbol": "SOLUSD",
        "name": "SOL",
        "oi_usd": 13273185.0,
        "oi_change_6h": -312954.0,
        "price": 69.135,
        "change_pct": -0.95
      },
      {
        "symbol": "PAXGUSD",
        "name": "PAXG",
        "oi_usd": 9417882.0,
        "oi_change_6h": -1086027.0,
        "price": 4155.2,
        "change_pct": -1.16
      },
      {
        "symbol": "XAUTUSD",
        "name": "XAUT",
        "oi_usd": 4643628.0,
        "oi_change_6h": 496517.0,
        "price": 4153.87,
        "change_pct": -1.15
      },
      {
        "symbol": "XRPUSD",
        "name": "XRP",
        "oi_usd": 2971877.0,
        "oi_change_6h": -33262.0,
        "price": 1.1327,
        "change_pct": -1.61
      },
      {
        "symbol": "SLVONUSD",
        "name": "SLVON",
        "oi_usd": 2408822.0,
        "oi_change_6h": 42373.0,
        "price": 58.79,
        "change_pct": -1.46
      },
      {
        "symbol": "RIVERUSD",
        "name": "RIVER",
        "oi_usd": 1033232.0,
        "oi_change_6h": 67549.0,
        "price": 4.492,
        "change_pct": -1.43
      },
      {
        "symbol": "DOGEUSD",
        "name": "DOGE",
        "oi_usd": 926931.0,
        "oi_change_6h": 18814.0,
        "price": 0.0832,
        "change_pct": -0.23
      },
      {
        "symbol": "BNBUSD",
        "name": "BNB",
        "oi_usd": 550866.0,
        "oi_change_6h": 55028.0,
        "price": 581.86,
        "change_pct": 0.19
      }
    ],
    "rising_oi": [
      {
        "symbol": "XAUTUSD",
        "name": "XAUT",
        "oi_usd": 4643628.0,
        "oi_change_6h": 496517.0,
        "price": 4153.87,
        "change_pct": -1.15
      },
      {
        "symbol": "RIVERUSD",
        "name": "RIVER",
        "oi_usd": 1033232.0,
        "oi_change_6h": 67549.0,
        "price": 4.492,
        "change_pct": -1.43
      },
      {
        "symbol": "MUSD",
        "name": "M",
        "oi_usd": 189540.0,
        "oi_change_6h": 65137.0,
        "price": 2.8718,
        "change_pct": -1.64
      },
      {
        "symbol": "BNBUSD",
        "name": "BNB",
        "oi_usd": 550866.0,
        "oi_change_6h": 55028.0,
        "price": 581.86,
        "change_pct": 0.19
      },
      {
        "symbol": "WLDUSD",
        "name": "WLD",
        "oi_usd": 89656.0,
        "oi_change_6h": 54728.0,
        "price": 0.6201,
        "change_pct": -2.08
      }
    ],
    "falling_oi": [
      {
        "symbol": "BTCUSD",
        "name": "BTC",
        "oi_usd": 56060997.0,
        "oi_change_6h": -2848393.0,
        "price": 63173.0,
        "change_pct": 0.21
      },
      {
        "symbol": "ETHUSD",
        "name": "ETH",
        "oi_usd": 33038313.0,
        "oi_change_6h": -2506279.0,
        "price": 1705.85,
        "change_pct": -0.24
      },
      {
        "symbol": "PAXGUSD",
        "name": "PAXG",
        "oi_usd": 9417882.0,
        "oi_change_6h": -1086027.0,
        "price": 4155.2,
        "change_pct": -1.16
      },
      {
        "symbol": "SOLUSD",
        "name": "SOL",
        "oi_usd": 13273185.0,
        "oi_change_6h": -312954.0,
        "price": 69.135,
        "change_pct": -0.95
      },
      {
        "symbol": "HUSD",
        "name": "H",
        "oi_usd": 515689.0,
        "oi_change_6h": -206895.0,
        "price": 0.2285,
        "change_pct": -0.97
      }
    ]
  },
  "funding": {
    "all": [
      {
        "symbol": "HUSD",
        "name": "H",
        "rate": -52.2778,
        "annualized": -57244.2,
        "sentiment": "Short Heavy",
        "signal": "BULLISH"
      },
      {
        "symbol": "XMRUSD",
        "name": "XMR",
        "rate": 28.0592,
        "annualized": 30724.9,
        "sentiment": "Strongly Long",
        "signal": "BEARISH"
      },
      {
        "symbol": "SAHARAUSD",
        "name": "SAHARA",
        "rate": -26.2966,
        "annualized": -28794.7,
        "sentiment": "Short Heavy",
        "signal": "BULLISH"
      },
      {
        "symbol": "SIRENUSD",
        "name": "SIREN",
        "rate": 18.3945,
        "annualized": 20141.9,
        "sentiment": "Strongly Long",
        "signal": "BEARISH"
      },
      {
        "symbol": "VVVUSD",
        "name": "VVV",
        "rate": -13.2553,
        "annualized": -14514.6,
        "sentiment": "Short Heavy",
        "signal": "BULLISH"
      },
      {
        "symbol": "OPUSD",
        "name": "OP",
        "rate": -12.8852,
        "annualized": -14109.3,
        "sentiment": "Short Heavy",
        "signal": "BULLISH"
      },
      {
        "symbol": "BEATUSD",
        "name": "BEAT",
        "rate": 9.4253,
        "annualized": 10320.7,
        "sentiment": "Strongly Long",
        "signal": "BEARISH"
      },
      {
        "symbol": "AIOTUSD",
        "name": "AIOT",
        "rate": -9.0258,
        "annualized": -9883.2,
        "sentiment": "Short Heavy",
        "signal": "BULLISH"
      },
      {
        "symbol": "VELVETUSD",
        "name": "VELVET",
        "rate": 8.8842,
        "annualized": 9728.2,
        "sentiment": "Strongly Long",
        "signal": "BEARISH"
      },
      {
        "symbol": "SWARMSUSD",
        "name": "SWARMS",
        "rate": 8.7667,
        "annualized": 9599.5,
        "sentiment": "Strongly Long",
        "signal": "BEARISH"
      },
      {
        "symbol": "RSRUSD",
        "name": "RSR",
        "rate": -8.4268,
        "annualized": -9227.3,
        "sentiment": "Short Heavy",
        "signal": "BULLISH"
      },
      {
        "symbol": "RAVEUSD",
        "name": "RAVE",
        "rate": 8.1142,
        "annualized": 8885.0,
        "sentiment": "Strongly Long",
        "signal": "BEARISH"
      },
      {
        "symbol": "COAIUSD",
        "name": "COAI",
        "rate": 7.9623,
        "annualized": 8718.7,
        "sentiment": "Strongly Long",
        "signal": "BEARISH"
      },
      {
        "symbol": "STBLUSD",
        "name": "STBL",
        "rate": -7.6675,
        "annualized": -8396.0,
        "sentiment": "Short Heavy",
        "signal": "BULLISH"
      },
      {
        "symbol": "GLMUSD",
        "name": "GLM",
        "rate": -7.5143,
        "annualized": -8228.1,
        "sentiment": "Short Heavy",
        "signal": "BULLISH"
      },
      {
        "symbol": "DYDXUSD",
        "name": "DYDX",
        "rate": 6.1619,
        "annualized": 6747.3,
        "sentiment": "Strongly Long",
        "signal": "BEARISH"
      },
      {
        "symbol": "BBUSD",
        "name": "BB",
        "rate": -5.6409,
        "annualized": -6176.8,
        "sentiment": "Short Heavy",
        "signal": "BULLISH"
      },
      {
        "symbol": "SEIUSD",
        "name": "SEI",
        "rate": 5.4441,
        "annualized": 5961.3,
        "sentiment": "Strongly Long",
        "signal": "BEARISH"
      },
      {
        "symbol": "ZKUSD",
        "name": "ZK",
        "rate": -5.3899,
        "annualized": -5901.9,
        "sentiment": "Short Heavy",
        "signal": "BULLISH"
      },
      {
        "symbol": "TRBUSD",
        "name": "TRB",
        "rate": -5.3415,
        "annualized": -5848.9,
        "sentiment": "Short Heavy",
        "signal": "BULLISH"
      }
    ],
    "high_funding": [
      {
        "symbol": "XMRUSD",
        "name": "XMR",
        "rate": 28.0592,
        "annualized": 30724.9,
        "sentiment": "Strongly Long",
        "signal": "BEARISH"
      },
      {
        "symbol": "SIRENUSD",
        "name": "SIREN",
        "rate": 18.3945,
        "annualized": 20141.9,
        "sentiment": "Strongly Long",
        "signal": "BEARISH"
      },
      {
        "symbol": "BEATUSD",
        "name": "BEAT",
        "rate": 9.4253,
        "annualized": 10320.7,
        "sentiment": "Strongly Long",
        "signal": "BEARISH"
      },
      {
        "symbol": "VELVETUSD",
        "name": "VELVET",
        "rate": 8.8842,
        "annualized": 9728.2,
        "sentiment": "Strongly Long",
        "signal": "BEARISH"
      },
      {
        "symbol": "SWARMSUSD",
        "name": "SWARMS",
        "rate": 8.7667,
        "annualized": 9599.5,
        "sentiment": "Strongly Long",
        "signal": "BEARISH"
      }
    ],
    "neg_funding": [
      {
        "symbol": "HUSD",
        "name": "H",
        "rate": -52.2778,
        "annualized": -57244.2,
        "sentiment": "Short Heavy",
        "signal": "BULLISH"
      },
      {
        "symbol": "SAHARAUSD",
        "name": "SAHARA",
        "rate": -26.2966,
        "annualized": -28794.7,
        "sentiment": "Short Heavy",
        "signal": "BULLISH"
      },
      {
        "symbol": "VVVUSD",
        "name": "VVV",
        "rate": -13.2553,
        "annualized": -14514.6,
        "sentiment": "Short Heavy",
        "signal": "BULLISH"
      },
      {
        "symbol": "OPUSD",
        "name": "OP",
        "rate": -12.8852,
        "annualized": -14109.3,
        "sentiment": "Short Heavy",
        "signal": "BULLISH"
      },
      {
        "symbol": "AIOTUSD",
        "name": "AIOT",
        "rate": -9.0258,
        "annualized": -9883.2,
        "sentiment": "Short Heavy",
        "signal": "BULLISH"
      }
    ]
  },
  "structure": {
    "top_gainers": [
      {
        "symbol": "ACTUSD",
        "name": "ACT",
        "change_pct": 21.64,
        "volume_usd": 2100462.0382
      },
      {
        "symbol": "BLESSUSD",
        "name": "BLESS",
        "change_pct": 18.82,
        "volume_usd": 2433175.510400003
      },
      {
        "symbol": "ORDIUSD",
        "name": "ORDI",
        "change_pct": 17.1,
        "volume_usd": 241383.0885
      },
      {
        "symbol": "WCTUSD",
        "name": "WCT",
        "change_pct": 17.05,
        "volume_usd": 682606.9406000003
      },
      {
        "symbol": "EVAAUSD",
        "name": "EVAA",
        "change_pct": 16.2,
        "volume_usd": 1373408.375300001
      }
    ],
    "top_losers": [
      {
        "symbol": "LABUSD",
        "name": "LAB",
        "change_pct": -26.45,
        "volume_usd": 21937142.17099981
      },
      {
        "symbol": "SIRENUSD",
        "name": "SIREN",
        "change_pct": -9.36,
        "volume_usd": 1148141.6183000016
      },
      {
        "symbol": "VELVETUSD",
        "name": "VELVET",
        "change_pct": -8.69,
        "volume_usd": 11941843.970999915
      },
      {
        "symbol": "BIOUSD",
        "name": "BIO",
        "change_pct": -8.15,
        "volume_usd": 126099.84210000004
      },
      {
        "symbol": "XLMUSD",
        "name": "XLM",
        "change_pct": -7.85,
        "volume_usd": 205781.32922999994
      }
    ],
    "top_volume": [
      {
        "symbol": "BTCUSD",
        "name": "BTC",
        "change_pct": 0.21,
        "volume_usd": 762281572.0580034
      },
      {
        "symbol": "ETHUSD",
        "name": "ETH",
        "change_pct": -0.24,
        "volume_usd": 373740525.83049846
      },
      {
        "symbol": "XAUTUSD",
        "name": "XAUT",
        "change_pct": -1.15,
        "volume_usd": 153347068.0522992
      },
      {
        "symbol": "PAXGUSD",
        "name": "PAXG",
        "change_pct": -1.16,
        "volume_usd": 116575085.04190016
      },
      {
        "symbol": "SOLUSD",
        "name": "SOL",
        "change_pct": -0.95,
        "volume_usd": 64392928.8216002
      }
    ]
  },
  "btc_options": null,
  "eth_options": null,
  "overview": {
    "top_gainers": [
      {
        "symbol": "ACTUSD",
        "name": "ACT",
        "change_pct": 21.64,
        "volume_usd": 2100462.0382
      },
      {
        "symbol": "BLESSUSD",
        "name": "BLESS",
        "change_pct": 18.82,
        "volume_usd": 2433175.510400003
      },
      {
        "symbol": "ORDIUSD",
        "name": "ORDI",
        "change_pct": 17.1,
        "volume_usd": 241383.0885
      },
      {
        "symbol": "WCTUSD",
        "name": "WCT",
        "change_pct": 17.05,
        "volume_usd": 682606.9406000003
      },
      {
        "symbol": "EVAAUSD",
        "name": "EVAA",
        "change_pct": 16.2,
        "volume_usd": 1373408.375300001
      }
    ],
    "top_losers": [
      {
        "symbol": "LABUSD",
        "name": "LAB",
        "change_pct": -26.45,
        "volume_usd": 21937142.17099981
      },
      {
        "symbol": "SIRENUSD",
        "name": "SIREN",
        "change_pct": -9.36,
        "volume_usd": 1148141.6183000016
      },
      {
        "symbol": "VELVETUSD",
        "name": "VELVET",
        "change_pct": -8.69,
        "volume_usd": 11941843.970999915
      },
      {
        "symbol": "BIOUSD",
        "name": "BIO",
        "change_pct": -8.15,
        "volume_usd": 126099.84210000004
      },
      {
        "symbol": "XLMUSD",
        "name": "XLM",
        "change_pct": -7.85,
        "volume_usd": 205781.32922999994
      }
    ],
    "top_volume": [
      {
        "symbol": "BTCUSD",
        "name": "BTC",
        "change_pct": 0.21,
        "volume_usd": 762281572.0580034
      },
      {
        "symbol": "ETHUSD",
        "name": "ETH",
        "change_pct": -0.24,
        "volume_usd": 373740525.83049846
      },
      {
        "symbol": "XAUTUSD",
        "name": "XAUT",
        "change_pct": -1.15,
        "volume_usd": 153347068.0522992
      },
      {
        "symbol": "PAXGUSD",
        "name": "PAXG",
        "change_pct": -1.16,
        "volume_usd": 116575085.04190016
      },
      {
        "symbol": "SOLUSD",
        "name": "SOL",
        "change_pct": -0.95,
        "volume_usd": 64392928.8216002
      }
    ]
  }
}