{
  "meta": {
    "date": "2026-07-08",
    "generated_at": "2026-07-08T01:05:00Z",
    "market": "Crypto Perpetual Futures"
  },
  "trend_summary": "Crypto market is Bearish with Low volatility. BTC -0.93% | ETH -1.26%. 0 coins advancing vs 1007 declining. Strongest sector: L2. Weakest: Emerging. Moon is Last Quarter \u2014 bearish energy. Day of Mercury. High funding: AIOT, H, TAC \u2014 longs crowded. Negative funding: LAB, BLUR, 1000BONK \u2014 squeeze risk.",
  "recommendation": "MOMENTUM LONG VVV",
  "rec_reason": "Confidence 85/100 \u2014 VVV Perpetual Futures",
  "no_trade_reasons": [],
  "setups": [
    {
      "type": "MOMENTUM",
      "direction": "LONG",
      "coin": "VVV",
      "symbol": "VVVUSD",
      "sector": "Infra",
      "instrument": "VVV Perpetual Futures",
      "entry": "Long VVV near $13.137222",
      "stop_loss": "SL: $12.420706 (ATR-based -5.3%) or below $13.0713",
      "target": "T1: $14.146441 (+7.9%) | T2: $14.836735 (+13.2%) | Key resistance: $13.148",
      "risk_reward": "R:R 1:1.5 to 1:2.5",
      "confidence": 85,
      "reasons": [
        "Strong Uptrend",
        "RSI 61.52 momentum zone",
        "MACD histogram positive",
        "Supertrend Bullish",
        "Above Ichimoku Cloud",
        "Bullish TK Cross"
      ],
      "funding_note": "Funding -2.5773%/8h (~-2822% annualized)",
      "current_price": 13.111,
      "rsi": 61.52,
      "rsi_hourly": 57.06,
      "trend": "Strong Uptrend",
      "adx": 25.0,
      "adx_strength": "Strong",
      "supertrend": "Bullish",
      "ichimoku_cloud": "Above Cloud (Bullish)",
      "macd_histogram": 0.029004,
      "atr_pct": 3.51,
      "bb_width": 11.49,
      "oi_trend": "Stable",
      "candlestick_patterns": [],
      "score_signals": [
        "EMA Stack Bullish",
        "RSI 61.52 momentum zone",
        "MACD Bullish",
        "Supertrend Bullish",
        "Above Ichimoku Cloud",
        "Stoch RSI bullish cross",
        "CCI 140.51 overbought",
        "OBV falling \u2014 selling pressure"
      ],
      "commentary": [
        "Funding is deeply negative (-2.5773%/8h) \u2014 shorts are paying heavily. This is classic squeeze fuel. Any positive catalyst could trigger rapid short covering.",
        "RSI 61.52 is in the ideal momentum zone \u2014 not overbought, not oversold. Clean entry conditions.",
        "Both Ichimoku Cloud and Supertrend agree \u2014 bullish structure confirmed on multiple timeframes.",
        "\u26a0\ufe0f Entry timing: CAUTION \u2014 Wait for ADX to strengthen above 25 before committing."
      ],
      "warning": "",
      "quality": "CLEAN",
      "risky_flags": []
    },
    {
      "type": "MOMENTUM",
      "direction": "LONG",
      "coin": "JUP",
      "symbol": "JUPUSD",
      "sector": "DeFi",
      "instrument": "JUP Perpetual Futures",
      "entry": "Long JUP near $0.24559",
      "stop_loss": "SL: $0.240198 (ATR-based -2.0%) or below $0.2425",
      "target": "T1: $0.252453 (+3.0%) | T2: $0.257355 (+5.0%) | Key resistance: $0.2574",
      "risk_reward": "R:R 1:1.5 to 1:2.5",
      "confidence": 73,
      "reasons": [
        "Strong Uptrend",
        "MACD histogram positive",
        "Supertrend Bullish",
        "Above Ichimoku Cloud",
        "Bullish TK Cross",
        "ADX 25.66 \u2014 Strong trend"
      ],
      "funding_note": "Funding -0.4802%/8h (~-526% annualized)",
      "current_price": 0.2451,
      "rsi": 66.46,
      "rsi_hourly": 29.39,
      "trend": "Strong Uptrend",
      "adx": 25.66,
      "adx_strength": "Strong",
      "supertrend": "Bullish",
      "ichimoku_cloud": "Above Cloud (Bullish)",
      "macd_histogram": 0.001084,
      "atr_pct": 0.93,
      "bb_width": 5.96,
      "oi_trend": "Stable",
      "candlestick_patterns": [
        "Doji"
      ],
      "score_signals": [
        "EMA Stack Bullish",
        "MACD Bullish",
        "Price above BB upper (overbought)",
        "ADX 25.66 \u2014 Strong trend",
        "Supertrend Bullish",
        "Above Ichimoku Cloud",
        "Stoch RSI bearish cross",
        "Williams %R overbought"
      ],
      "commentary": [
        "Bollinger Bands are tightening (5.96%) \u2014 volatility building, breakout likely soon.",
        "ADX 25.66 \u2014 Moderate trend. Valid but watch for signs of weakening.",
        "Funding is deeply negative (-0.4802%/8h) \u2014 shorts are paying heavily. This is classic squeeze fuel. Any positive catalyst could trigger rapid short covering.",
        "Both Ichimoku Cloud and Supertrend agree \u2014 bullish structure confirmed on multiple timeframes.",
        "\u2705 Entry timing: Valid \u2014 Enter on next candle close. Keep size at 15-20% capital."
      ],
      "warning": "",
      "quality": "CLEAN",
      "risky_flags": []
    },
    {
      "type": "MOMENTUM",
      "direction": "LONG",
      "coin": "PENDLE",
      "symbol": "PENDLEUSD",
      "sector": "DeFi",
      "instrument": "PENDLE Perpetual Futures",
      "entry": "Long PENDLE near $1.480555",
      "stop_loss": "SL: $1.448048 (ATR-based -2.0%) or below $1.4436",
      "target": "T1: $1.521928 (+3.0%) | T2: $1.55148 (+5.0%) | Key resistance: $1.4795",
      "risk_reward": "R:R 1:1.5 to 1:2.5",
      "confidence": 70,
      "reasons": [
        "Strong Uptrend",
        "RSI 59.55 momentum zone",
        "Supertrend Bullish",
        "Above Ichimoku Cloud",
        "ADX 27.57 \u2014 Strong trend",
        "Parabolic SAR Bullish"
      ],
      "funding_note": "Funding -4.4534%/8h (~-4876% annualized)",
      "current_price": 1.4776,
      "rsi": 59.55,
      "rsi_hourly": 39.32,
      "trend": "Strong Uptrend",
      "adx": 27.57,
      "adx_strength": "Strong",
      "supertrend": "Bullish",
      "ichimoku_cloud": "Above Cloud (Bullish)",
      "macd_histogram": -1.1e-05,
      "atr_pct": 0.94,
      "bb_width": 3.31,
      "oi_trend": "Stable",
      "candlestick_patterns": [],
      "score_signals": [
        "EMA Stack Bullish",
        "RSI 59.55 momentum zone",
        "MACD Bearish",
        "BB squeeze \u2014 breakout imminent",
        "ADX 27.57 \u2014 Strong trend",
        "Supertrend Bullish",
        "Above Ichimoku Cloud",
        "Stoch RSI bullish cross"
      ],
      "commentary": [
        "\u26a0\ufe0f Conflicting signals detected:",
        "  \u2192 MACD momentum is negative despite bullish trend \u2014 momentum lagging",
        "BB squeeze detected (3.31% width) \u2014 a large move is coming but direction not yet confirmed. Wait for price to break clearly above/below the bands before entering.",
        "ADX 27.57 \u2014 Moderate trend. Valid but watch for signs of weakening.",
        "Funding is deeply negative (-4.4534%/8h) \u2014 shorts are paying heavily. This is classic squeeze fuel. Any positive catalyst could trigger rapid short covering.",
        "RSI 59.55 is in the ideal momentum zone \u2014 not overbought, not oversold. Clean entry conditions.",
        "Both Ichimoku Cloud and Supertrend agree \u2014 bullish structure confirmed on multiple timeframes.",
        "\u23f3 Entry timing: WAIT \u2014 BB squeeze means direction unclear. Enter only after clear breakout candle closes."
      ],
      "warning": "",
      "quality": "CLEAN",
      "risky_flags": []
    },
    {
      "type": "MOMENTUM",
      "direction": "SHORT",
      "coin": "SKL",
      "symbol": "SKLUSD",
      "sector": "L2",
      "instrument": "SKL Perpetual Futures",
      "entry": "Short SKL near $0.003643",
      "stop_loss": "SL: $0.003723 (ATR-based +2.0%) or above $0.004",
      "target": "T1: $0.00354 (-3.0%) | T2: $0.003467 (-5.0%) | Key support: $0.0036",
      "risk_reward": "R:R 1:1.5 to 1:2.5",
      "confidence": 53,
      "reasons": [
        "MACD histogram negative",
        "Below Ichimoku Cloud",
        "Bearish TK Cross",
        "Parabolic SAR Bearish",
        "Funding 10.8941% \u2014 longs overcrowded, short opportunity",
        "Last Quarter \u2014 bearish moon"
      ],
      "funding_note": "Funding +10.8941%/8h (~11929% annualized)",
      "current_price": 0.00365,
      "rsi": 53.83,
      "rsi_hourly": 63.0,
      "trend": "Uptrend",
      "adx": 30.25,
      "adx_strength": "Strong",
      "supertrend": "Bullish",
      "ichimoku_cloud": "Below Cloud (Bearish)",
      "macd_histogram": -1e-06,
      "atr_pct": 1.1,
      "bb_width": 5.45,
      "oi_trend": "Stable",
      "candlestick_patterns": [
        "Doji"
      ],
      "score_signals": [
        "Price above EMA20/50",
        "RSI 53.83 momentum zone",
        "MACD Bearish",
        "ADX 30.25 \u2014 Strong trend",
        "Supertrend Bullish",
        "Below Ichimoku Cloud",
        "Stoch RSI bullish cross",
        "OBV rising \u2014 buying pressure"
      ],
      "commentary": [
        "\u26a0\ufe0f Conflicting signals detected:",
        "  \u2192 Supertrend bullish conflicts with short direction \u2014 wait for Supertrend to flip",
        "Bollinger Bands are tightening (5.45%) \u2014 volatility building, breakout likely soon.",
        "ADX 30.25 \u2014 Moderate trend. Valid but watch for signs of weakening.",
        "High positive funding (10.8941%/8h) confirms shorts are needed \u2014 longs will be flushed.",
        "\u23f3 Entry timing: WAIT for conflict to resolve \u2014 check 5m chart for confirmation candle before entering."
      ],
      "warning": "",
      "quality": "CLEAN",
      "risky_flags": []
    },
    {
      "type": "MEAN_REVERSION",
      "direction": "SQUEEZE",
      "coin": "PENDLE",
      "symbol": "PENDLEUSD",
      "sector": "DeFi",
      "instrument": "PENDLE Perpetual Futures",
      "entry": "Long PENDLE near $1.480555",
      "stop_loss": "SL: $1.448048 (ATR-based -2.0%) or below $1.4436",
      "target": "T1: $1.521928 (+3.0%) | T2: $1.55148 (+5.0%) | Key resistance: $1.4795",
      "risk_reward": "R:R 1:1.5 to 1:2.5",
      "confidence": 50,
      "reasons": [
        "Funding -4.4534% \u2014 shorts paying",
        "Extreme negative funding \u2014 violent squeeze likely"
      ],
      "funding_note": "Funding -4.4534%/8h (~-4876% annualized)",
      "current_price": 1.4776,
      "rsi": 59.55,
      "rsi_hourly": 39.32,
      "trend": "Strong Uptrend",
      "adx": 27.57,
      "adx_strength": "Strong",
      "supertrend": "Bullish",
      "ichimoku_cloud": "Above Cloud (Bullish)",
      "macd_histogram": -1.1e-05,
      "atr_pct": 0.94,
      "bb_width": 3.31,
      "oi_trend": "Stable",
      "candlestick_patterns": [],
      "score_signals": [
        "EMA Stack Bullish",
        "RSI 59.55 momentum zone",
        "MACD Bearish",
        "BB squeeze \u2014 breakout imminent",
        "ADX 27.57 \u2014 Strong trend",
        "Supertrend Bullish",
        "Above Ichimoku Cloud",
        "Stoch RSI bullish cross"
      ],
      "commentary": [
        "\u26a0\ufe0f Conflicting signals detected:",
        "  \u2192 MACD momentum is negative despite bullish trend \u2014 momentum lagging",
        "BB squeeze detected (3.31% width) \u2014 a large move is coming but direction not yet confirmed. Wait for price to break clearly above/below the bands before entering.",
        "ADX 27.57 \u2014 Moderate trend. Valid but watch for signs of weakening.",
        "Funding is deeply negative (-4.4534%/8h) \u2014 shorts are paying heavily. This is classic squeeze fuel. Any positive catalyst could trigger rapid short covering.",
        "RSI 59.55 is in the ideal momentum zone \u2014 not overbought, not oversold. Clean entry conditions.",
        "Both Ichimoku Cloud and Supertrend agree \u2014 bullish structure confirmed on multiple timeframes.",
        "\u23f3 Entry timing: WAIT \u2014 BB squeeze means direction unclear. Enter only after clear breakout candle closes."
      ],
      "warning": "",
      "quality": "CLEAN",
      "risky_flags": []
    },
    {
      "type": "MEAN_REVERSION",
      "direction": "FLUSH",
      "coin": "COOKIE",
      "symbol": "COOKIEUSD",
      "sector": "AI",
      "instrument": "COOKIE Perpetual Futures",
      "entry": "Short COOKIE near $0.010649",
      "stop_loss": "SL: $0.011269 (ATR-based +5.6%) or above $0.0112",
      "target": "T1: $0.009772 (-8.4%) | T2: $0.009174 (-14.0%) | Key support: $0.0103",
      "risk_reward": "R:R 1:1.5 to 1:2.5",
      "confidence": 50,
      "reasons": [
        "Extreme funding 4.4876% \u2014 long liquidation imminent",
        "CCI 218.4 extreme overbought",
        "Price above BB upper band"
      ],
      "funding_note": "Funding +4.4876%/8h (~4914% annualized)",
      "current_price": 0.01067,
      "rsi": 65.82,
      "rsi_hourly": 54.37,
      "trend": "Strong Uptrend",
      "adx": 29.99,
      "adx_strength": "Strong",
      "supertrend": "Bullish",
      "ichimoku_cloud": "Above Cloud (Bullish)",
      "macd_histogram": 6.1e-05,
      "atr_pct": 3.74,
      "bb_width": 8.64,
      "oi_trend": "Stable",
      "candlestick_patterns": [
        "Morning Star"
      ],
      "score_signals": [
        "EMA Stack Bullish",
        "MACD Bullish",
        "Price above BB upper (overbought)",
        "ADX 29.99 \u2014 Strong trend",
        "Supertrend Bullish",
        "Above Ichimoku Cloud",
        "Stoch RSI bullish cross",
        "CCI 218.4 overbought"
      ],
      "commentary": [
        "\u26a0\ufe0f Conflicting signals detected:",
        "  \u2192 Morning Star pattern conflicts with short direction",
        "Bollinger Bands are tightening (8.64%) \u2014 volatility building, breakout likely soon.",
        "ADX 29.99 \u2014 Moderate trend. Valid but watch for signs of weakening.",
        "High positive funding (4.4876%/8h) confirms shorts are needed \u2014 longs will be flushed.",
        "\u23f3 Entry timing: WAIT for conflict to resolve \u2014 check 5m chart for confirmation candle before entering."
      ],
      "warning": "",
      "quality": "CLEAN",
      "risky_flags": []
    },
    {
      "type": "MEAN_REVERSION",
      "direction": "SQUEEZE",
      "coin": "VVV",
      "symbol": "VVVUSD",
      "sector": "Infra",
      "instrument": "VVV Perpetual Futures",
      "entry": "Long VVV near $13.137222",
      "stop_loss": "SL: $12.420706 (ATR-based -5.3%) or below $13.0713",
      "target": "T1: $14.146441 (+7.9%) | T2: $14.836735 (+13.2%) | Key resistance: $13.148",
      "risk_reward": "R:R 1:1.5 to 1:2.5",
      "confidence": 50,
      "reasons": [
        "Funding -2.5773% \u2014 shorts paying",
        "Extreme negative funding \u2014 violent squeeze likely"
      ],
      "funding_note": "Funding -2.5773%/8h (~-2822% annualized)",
      "current_price": 13.111,
      "rsi": 61.52,
      "rsi_hourly": 57.06,
      "trend": "Strong Uptrend",
      "adx": 25.0,
      "adx_strength": "Strong",
      "supertrend": "Bullish",
      "ichimoku_cloud": "Above Cloud (Bullish)",
      "macd_histogram": 0.029004,
      "atr_pct": 3.51,
      "bb_width": 11.49,
      "oi_trend": "Stable",
      "candlestick_patterns": [],
      "score_signals": [
        "EMA Stack Bullish",
        "RSI 61.52 momentum zone",
        "MACD Bullish",
        "Supertrend Bullish",
        "Above Ichimoku Cloud",
        "Stoch RSI bullish cross",
        "CCI 140.51 overbought",
        "OBV falling \u2014 selling pressure"
      ],
      "commentary": [
        "Funding is deeply negative (-2.5773%/8h) \u2014 shorts are paying heavily. This is classic squeeze fuel. Any positive catalyst could trigger rapid short covering.",
        "RSI 61.52 is in the ideal momentum zone \u2014 not overbought, not oversold. Clean entry conditions.",
        "Both Ichimoku Cloud and Supertrend agree \u2014 bullish structure confirmed on multiple timeframes.",
        "\u26a0\ufe0f Entry timing: CAUTION \u2014 Wait for ADX to strengthen above 25 before committing."
      ],
      "warning": "",
      "quality": "CLEAN",
      "risky_flags": []
    },
    {
      "type": "MEAN_REVERSION",
      "direction": "SQUEEZE",
      "coin": "JUP",
      "symbol": "JUPUSD",
      "sector": "DeFi",
      "instrument": "JUP Perpetual Futures",
      "entry": "Long JUP near $0.24559",
      "stop_loss": "SL: $0.240198 (ATR-based -2.0%) or below $0.2425",
      "target": "T1: $0.252453 (+3.0%) | T2: $0.257355 (+5.0%) | Key resistance: $0.2574",
      "risk_reward": "R:R 1:1.5 to 1:2.5",
      "confidence": 50,
      "reasons": [
        "Funding -0.4802% \u2014 shorts paying",
        "Extreme negative funding \u2014 violent squeeze likely"
      ],
      "funding_note": "Funding -0.4802%/8h (~-526% annualized)",
      "current_price": 0.2451,
      "rsi": 66.46,
      "rsi_hourly": 29.39,
      "trend": "Strong Uptrend",
      "adx": 25.66,
      "adx_strength": "Strong",
      "supertrend": "Bullish",
      "ichimoku_cloud": "Above Cloud (Bullish)",
      "macd_histogram": 0.001084,
      "atr_pct": 0.93,
      "bb_width": 5.96,
      "oi_trend": "Stable",
      "candlestick_patterns": [
        "Doji"
      ],
      "score_signals": [
        "EMA Stack Bullish",
        "MACD Bullish",
        "Price above BB upper (overbought)",
        "ADX 25.66 \u2014 Strong trend",
        "Supertrend Bullish",
        "Above Ichimoku Cloud",
        "Stoch RSI bearish cross",
        "Williams %R overbought"
      ],
      "commentary": [
        "Bollinger Bands are tightening (5.96%) \u2014 volatility building, breakout likely soon.",
        "ADX 25.66 \u2014 Moderate trend. Valid but watch for signs of weakening.",
        "Funding is deeply negative (-0.4802%/8h) \u2014 shorts are paying heavily. This is classic squeeze fuel. Any positive catalyst could trigger rapid short covering.",
        "Both Ichimoku Cloud and Supertrend agree \u2014 bullish structure confirmed on multiple timeframes.",
        "\u2705 Entry timing: Valid \u2014 Enter on next candle close. Keep size at 15-20% capital."
      ],
      "warning": "",
      "quality": "CLEAN",
      "risky_flags": []
    },
    {
      "type": "MEAN_REVERSION",
      "direction": "FLUSH",
      "coin": "LAYER",
      "symbol": "LAYERUSD",
      "sector": "L2",
      "instrument": "LAYER Perpetual Futures",
      "entry": "Short LAYER near $0.067764",
      "stop_loss": "SL: $0.069258 (ATR-based +2.0%) or above $0.068",
      "target": "T1: $0.065863 (-3.0%) | T2: $0.064505 (-5.0%) | Key support: $0.0676",
      "risk_reward": "R:R 1:1.5 to 1:2.5",
      "confidence": 40,
      "reasons": [
        "Extreme funding 0.5% \u2014 long liquidation imminent",
        "Williams %R -5.26 extreme overbought"
      ],
      "funding_note": "Funding +0.5%/8h (~548% annualized)",
      "current_price": 0.0679,
      "rsi": 63.08,
      "rsi_hourly": 51.01,
      "trend": "Strong Uptrend",
      "adx": 25.48,
      "adx_strength": "Strong",
      "supertrend": "Bullish",
      "ichimoku_cloud": "Above Cloud (Bullish)",
      "macd_histogram": 0.000128,
      "atr_pct": 0.62,
      "bb_width": 3.74,
      "oi_trend": "Stable",
      "candlestick_patterns": [],
      "score_signals": [
        "EMA Stack Bullish",
        "RSI 63.08 momentum zone",
        "MACD Bullish",
        "BB squeeze \u2014 breakout imminent",
        "ADX 25.48 \u2014 Strong trend",
        "Supertrend Bullish",
        "Above Ichimoku Cloud",
        "Williams %R overbought"
      ],
      "commentary": [
        "BB squeeze detected (3.74% width) \u2014 a large move is coming but direction not yet confirmed. Wait for price to break clearly above/below the bands before entering.",
        "ADX 25.48 \u2014 Moderate trend. Valid but watch for signs of weakening.",
        "High positive funding (0.5%/8h) confirms shorts are needed \u2014 longs will be flushed.",
        "\u23f3 Entry timing: WAIT \u2014 BB squeeze means direction unclear. Enter only after clear breakout candle closes."
      ],
      "warning": "",
      "quality": "CLEAN",
      "risky_flags": []
    }
  ],
  "risky_setups": [
    {
      "type": "MOMENTUM",
      "direction": "LONG",
      "coin": "APT",
      "symbol": "APTUSD",
      "sector": "L1",
      "instrument": "APT Perpetual Futures",
      "entry": "Long APT near $0.64128",
      "stop_loss": "SL: $0.6272 (ATR-based -2.0%) or below $0.623",
      "target": "T1: $0.6592 (+3.0%) | T2: $0.672 (+5.0%) | Key resistance: $0.646",
      "risk_reward": "R:R 1:1.5 to 1:2.5",
      "confidence": 96,
      "reasons": [
        "Strong Uptrend",
        "RSI 62.5 momentum zone",
        "MACD histogram positive",
        "Supertrend Bullish",
        "Above Ichimoku Cloud",
        "Bullish TK Cross"
      ],
      "funding_note": "Funding -0.4451%/8h (~-487% annualized)",
      "current_price": 0.64,
      "rsi": 62.5,
      "rsi_hourly": 54.09,
      "trend": "Strong Uptrend",
      "adx": 15.06,
      "adx_strength": "Weak",
      "supertrend": "Bullish",
      "ichimoku_cloud": "Above Cloud (Bullish)",
      "macd_histogram": 0.000894,
      "atr_pct": 0.57,
      "bb_width": 3.72,
      "oi_trend": "Rising",
      "candlestick_patterns": [
        "Doji"
      ],
      "score_signals": [
        "EMA Stack Bullish",
        "RSI 62.5 momentum zone",
        "MACD Bullish",
        "BB squeeze \u2014 breakout imminent",
        "Supertrend Bullish",
        "Above Ichimoku Cloud",
        "OBV rising \u2014 buying pressure",
        "Parabolic SAR Bullish"
      ],
      "commentary": [
        "BB squeeze detected (3.72% width) \u2014 a large move is coming but direction not yet confirmed. Wait for price to break clearly above/below the bands before entering.",
        "ADX 15.06 \u2014 Trend is weak. Price may chop rather than trend. Reduce size.",
        "Funding is deeply negative (-0.4451%/8h) \u2014 shorts are paying heavily. This is classic squeeze fuel. Any positive catalyst could trigger rapid short covering.",
        "Open Interest rising \u2014 fresh money entering long positions. Trend has conviction.",
        "RSI 62.5 is in the ideal momentum zone \u2014 not overbought, not oversold. Clean entry conditions.",
        "Both Ichimoku Cloud and Supertrend agree \u2014 bullish structure confirmed on multiple timeframes.",
        "\u23f3 Entry timing: WAIT \u2014 BB squeeze means direction unclear. Enter only after clear breakout candle closes."
      ],
      "warning": "",
      "quality": "RISKY",
      "risky_flags": [
        "ADX 15.06 < 20 \u2014 no trend (Wilder threshold)"
      ]
    },
    {
      "type": "MOMENTUM",
      "direction": "LONG",
      "coin": "VIRTUAL",
      "symbol": "VIRTUALUSD",
      "sector": "AI",
      "instrument": "VIRTUAL Perpetual Futures",
      "entry": "Long VIRTUAL near $0.580459",
      "stop_loss": "SL: $0.567714 (ATR-based -2.0%) or below $0.5781",
      "target": "T1: $0.596679 (+3.0%) | T2: $0.608265 (+5.0%) | Key resistance: $0.5808",
      "risk_reward": "R:R 1:1.5 to 1:2.5",
      "confidence": 90,
      "reasons": [
        "Strong Uptrend",
        "RSI 62.55 momentum zone",
        "MACD histogram positive",
        "Supertrend Bullish",
        "Above Ichimoku Cloud",
        "Bullish TK Cross"
      ],
      "funding_note": "Funding -3.1851%/8h (~-3488% annualized)",
      "current_price": 0.5793,
      "rsi": 62.55,
      "rsi_hourly": 49.66,
      "trend": "Strong Uptrend",
      "adx": 20.25,
      "adx_strength": "Moderate",
      "supertrend": "Bullish",
      "ichimoku_cloud": "Above Cloud (Bullish)",
      "macd_histogram": 0.000878,
      "atr_pct": 0.66,
      "bb_width": 3.52,
      "oi_trend": "Stable",
      "candlestick_patterns": [
        "Doji"
      ],
      "score_signals": [
        "EMA Stack Bullish",
        "RSI 62.55 momentum zone",
        "MACD Bullish",
        "BB squeeze \u2014 breakout imminent",
        "Supertrend Bullish",
        "Above Ichimoku Cloud",
        "Williams %R overbought",
        "CCI 132.23 overbought"
      ],
      "commentary": [
        "BB squeeze detected (3.52% width) \u2014 a large move is coming but direction not yet confirmed. Wait for price to break clearly above/below the bands before entering.",
        "Funding is deeply negative (-3.1851%/8h) \u2014 shorts are paying heavily. This is classic squeeze fuel. Any positive catalyst could trigger rapid short covering.",
        "RSI 62.55 is in the ideal momentum zone \u2014 not overbought, not oversold. Clean entry conditions.",
        "Both Ichimoku Cloud and Supertrend agree \u2014 bullish structure confirmed on multiple timeframes.",
        "\u23f3 Entry timing: WAIT \u2014 BB squeeze means direction unclear. Enter only after clear breakout candle closes."
      ],
      "warning": "",
      "quality": "RISKY",
      "risky_flags": [
        "ADX 20.25 < 25 \u2014 weak trend, reduce size"
      ]
    },
    {
      "type": "MOMENTUM",
      "direction": "LONG",
      "coin": "STRK",
      "symbol": "STRKUSD",
      "sector": "L2",
      "instrument": "STRK Perpetual Futures",
      "entry": "Long STRK near $0.031763",
      "stop_loss": "SL: $0.031066 (ATR-based -2.0%) or below $0.0308",
      "target": "T1: $0.032651 (+3.0%) | T2: $0.033285 (+5.0%) | Key resistance: $0.0318",
      "risk_reward": "R:R 1:1.5 to 1:2.5",
      "confidence": 87,
      "reasons": [
        "Strong Uptrend",
        "RSI 58.13 momentum zone",
        "MACD histogram positive",
        "Supertrend Bullish",
        "Above Ichimoku Cloud",
        "Bullish TK Cross"
      ],
      "funding_note": "Funding -1.9218%/8h (~-2104% annualized)",
      "current_price": 0.0317,
      "rsi": 58.13,
      "rsi_hourly": 54.6,
      "trend": "Strong Uptrend",
      "adx": 13.6,
      "adx_strength": "Weak",
      "supertrend": "Bullish",
      "ichimoku_cloud": "Above Cloud (Bullish)",
      "macd_histogram": 5.5e-05,
      "atr_pct": 0.56,
      "bb_width": 4.22,
      "oi_trend": "Stable",
      "candlestick_patterns": [
        "Doji"
      ],
      "score_signals": [
        "EMA Stack Bullish",
        "RSI 58.13 momentum zone",
        "MACD Bullish",
        "BB squeeze \u2014 breakout imminent",
        "Supertrend Bullish",
        "Above Ichimoku Cloud",
        "Stoch RSI bullish cross",
        "Williams %R overbought"
      ],
      "commentary": [
        "BB squeeze detected (4.22% width) \u2014 a large move is coming but direction not yet confirmed. Wait for price to break clearly above/below the bands before entering.",
        "ADX 13.6 \u2014 Trend is weak. Price may chop rather than trend. Reduce size.",
        "Funding is deeply negative (-1.9218%/8h) \u2014 shorts are paying heavily. This is classic squeeze fuel. Any positive catalyst could trigger rapid short covering.",
        "RSI 58.13 is in the ideal momentum zone \u2014 not overbought, not oversold. Clean entry conditions.",
        "Both Ichimoku Cloud and Supertrend agree \u2014 bullish structure confirmed on multiple timeframes.",
        "\u23f3 Entry timing: WAIT \u2014 BB squeeze means direction unclear. Enter only after clear breakout candle closes."
      ],
      "warning": "",
      "quality": "RISKY",
      "risky_flags": [
        "ADX 13.6 < 20 \u2014 no trend (Wilder threshold)"
      ]
    },
    {
      "type": "MOMENTUM",
      "direction": "LONG",
      "coin": "ME",
      "symbol": "MEUSD",
      "sector": "Emerging",
      "instrument": "ME Perpetual Futures",
      "entry": "Long ME near $0.066032",
      "stop_loss": "SL: $0.064582 (ATR-based -2.0%) or below $0.0649",
      "target": "T1: $0.067877 (+3.0%) | T2: $0.069195 (+5.0%) | Key resistance: $0.0665",
      "risk_reward": "R:R 1:1.5 to 1:2.5",
      "confidence": 86,
      "reasons": [
        "Strong Uptrend",
        "RSI 63.45 momentum zone",
        "MACD histogram positive",
        "Supertrend Bullish",
        "Above Ichimoku Cloud",
        "Bullish TK Cross"
      ],
      "funding_note": "Funding -6.9034%/8h (~-7559% annualized)",
      "current_price": 0.0659,
      "rsi": 63.45,
      "rsi_hourly": 42.27,
      "trend": "Strong Uptrend",
      "adx": 18.67,
      "adx_strength": "Weak",
      "supertrend": "Bullish",
      "ichimoku_cloud": "Above Cloud (Bullish)",
      "macd_histogram": 4e-06,
      "atr_pct": 1.09,
      "bb_width": 2.74,
      "oi_trend": "Stable",
      "candlestick_patterns": [],
      "score_signals": [
        "EMA Stack Bullish",
        "RSI 63.45 momentum zone",
        "MACD Bullish",
        "Price above BB upper (overbought)",
        "BB squeeze \u2014 breakout imminent",
        "Supertrend Bullish",
        "Above Ichimoku Cloud",
        "Stoch RSI bullish cross"
      ],
      "commentary": [
        "BB squeeze detected (2.74% width) \u2014 a large move is coming but direction not yet confirmed. Wait for price to break clearly above/below the bands before entering.",
        "ADX 18.67 \u2014 Trend is weak. Price may chop rather than trend. Reduce size.",
        "Funding is deeply negative (-6.9034%/8h) \u2014 shorts are paying heavily. This is classic squeeze fuel. Any positive catalyst could trigger rapid short covering.",
        "RSI 63.45 is in the ideal momentum zone \u2014 not overbought, not oversold. Clean entry conditions.",
        "Both Ichimoku Cloud and Supertrend agree \u2014 bullish structure confirmed on multiple timeframes.",
        "\u23f3 Entry timing: WAIT \u2014 BB squeeze means direction unclear. Enter only after clear breakout candle closes."
      ],
      "warning": "",
      "quality": "RISKY",
      "risky_flags": [
        "ADX 18.67 < 20 \u2014 no trend (Wilder threshold)"
      ]
    },
    {
      "type": "MOMENTUM",
      "direction": "LONG",
      "coin": "TIA",
      "symbol": "TIAUSD",
      "sector": "L1",
      "instrument": "TIA Perpetual Futures",
      "entry": "Long TIA near $0.401501",
      "stop_loss": "SL: $0.392526 (ATR-based -2.0%) or below $0.3991",
      "target": "T1: $0.412961 (+3.1%) | T2: $0.421136 (+5.1%) | Key resistance: $0.4032",
      "risk_reward": "R:R 1:1.5 to 1:2.5",
      "confidence": 85,
      "reasons": [
        "Strong Uptrend",
        "RSI 55.81 momentum zone",
        "MACD histogram positive",
        "Supertrend Bullish",
        "Above Ichimoku Cloud",
        "Bullish TK Cross"
      ],
      "funding_note": "Funding -3.1487%/8h (~-3448% annualized)",
      "current_price": 0.4007,
      "rsi": 55.81,
      "rsi_hourly": 39.34,
      "trend": "Strong Uptrend",
      "adx": 17.95,
      "adx_strength": "Weak",
      "supertrend": "Bullish",
      "ichimoku_cloud": "Above Cloud (Bullish)",
      "macd_histogram": 0.000415,
      "atr_pct": 1.36,
      "bb_width": 5.96,
      "oi_trend": "Stable",
      "candlestick_patterns": [
        "Doji"
      ],
      "score_signals": [
        "EMA Stack Bullish",
        "RSI 55.81 momentum zone",
        "MACD Bullish",
        "Supertrend Bullish",
        "Above Ichimoku Cloud",
        "OBV rising \u2014 buying pressure",
        "Parabolic SAR Bullish",
        "Price above VWAP"
      ],
      "commentary": [
        "Bollinger Bands are tightening (5.96%) \u2014 volatility building, breakout likely soon.",
        "ADX 17.95 \u2014 Trend is weak. Price may chop rather than trend. Reduce size.",
        "Funding is deeply negative (-3.1487%/8h) \u2014 shorts are paying heavily. This is classic squeeze fuel. Any positive catalyst could trigger rapid short covering.",
        "RSI 55.81 is in the ideal momentum zone \u2014 not overbought, not oversold. Clean entry conditions.",
        "Both Ichimoku Cloud and Supertrend agree \u2014 bullish structure confirmed on multiple timeframes.",
        "\u26a0\ufe0f Entry timing: CAUTION \u2014 Wait for ADX to strengthen above 25 before committing."
      ],
      "warning": "",
      "quality": "RISKY",
      "risky_flags": [
        "ADX 17.95 < 20 \u2014 no trend (Wilder threshold)"
      ]
    },
    {
      "type": "MOMENTUM",
      "direction": "LONG",
      "coin": "INJ",
      "symbol": "INJUSD",
      "sector": "Infra",
      "instrument": "INJ Perpetual Futures",
      "entry": "Long INJ near $4.875732",
      "stop_loss": "SL: $4.76868 (ATR-based -2.0%) or below $4.8557",
      "target": "T1: $5.01198 (+3.0%) | T2: $5.1093 (+5.0%) | Key resistance: $4.8673",
      "risk_reward": "R:R 1:1.5 to 1:2.5",
      "confidence": 85,
      "reasons": [
        "Strong Uptrend",
        "RSI 54.91 momentum zone",
        "MACD histogram positive",
        "Supertrend Bullish",
        "Above Ichimoku Cloud",
        "Bullish TK Cross"
      ],
      "funding_note": "Funding -4.5746%/8h (~-5009% annualized)",
      "current_price": 4.866,
      "rsi": 54.91,
      "rsi_hourly": 58.78,
      "trend": "Strong Uptrend",
      "adx": 12.0,
      "adx_strength": "Weak",
      "supertrend": "Bullish",
      "ichimoku_cloud": "Above Cloud (Bullish)",
      "macd_histogram": 0.000251,
      "atr_pct": 0.99,
      "bb_width": 3.76,
      "oi_trend": "Falling",
      "candlestick_patterns": [
        "Doji"
      ],
      "score_signals": [
        "EMA Stack Bullish",
        "RSI 54.91 momentum zone",
        "MACD Bullish",
        "BB squeeze \u2014 breakout imminent",
        "Supertrend Bullish",
        "Above Ichimoku Cloud",
        "OBV falling \u2014 selling pressure",
        "Parabolic SAR Bullish"
      ],
      "commentary": [
        "BB squeeze detected (3.76% width) \u2014 a large move is coming but direction not yet confirmed. Wait for price to break clearly above/below the bands before entering.",
        "ADX 12.0 \u2014 Trend is weak. Price may chop rather than trend. Reduce size.",
        "Funding is deeply negative (-4.5746%/8h) \u2014 shorts are paying heavily. This is classic squeeze fuel. Any positive catalyst could trigger rapid short covering.",
        "Open Interest falling \u2014 longs are exiting. Momentum is fading. Wait for OI to stabilize.",
        "RSI 54.91 is in the ideal momentum zone \u2014 not overbought, not oversold. Clean entry conditions.",
        "Both Ichimoku Cloud and Supertrend agree \u2014 bullish structure confirmed on multiple timeframes.",
        "\u23f3 Entry timing: WAIT \u2014 BB squeeze means direction unclear. Enter only after clear breakout candle closes."
      ],
      "warning": "",
      "quality": "RISKY",
      "risky_flags": [
        "ADX 12.0 < 20 \u2014 no trend (Wilder threshold)",
        "OI Falling \u2014 momentum fading, avoid new longs"
      ]
    },
    {
      "type": "MOMENTUM",
      "direction": "LONG",
      "coin": "ZEN",
      "symbol": "ZENUSD",
      "sector": "Emerging",
      "instrument": "ZEN Perpetual Futures",
      "entry": "Long ZEN near $4.35369",
      "stop_loss": "SL: $4.2581 (ATR-based -2.0%) or below $4.241",
      "target": "T1: $4.47535 (+3.0%) | T2: $4.56225 (+5.0%) | Key resistance: $4.5622",
      "risk_reward": "R:R 1:1.5 to 1:2.5",
      "confidence": 84,
      "reasons": [
        "Strong Uptrend",
        "RSI 63.09 momentum zone",
        "MACD histogram positive",
        "Supertrend Bullish",
        "Above Ichimoku Cloud",
        "Parabolic SAR Bullish"
      ],
      "funding_note": "Funding -1.4526%/8h (~-1591% annualized)",
      "current_price": 4.345,
      "rsi": 63.09,
      "rsi_hourly": 50.03,
      "trend": "Strong Uptrend",
      "adx": 14.23,
      "adx_strength": "Weak",
      "supertrend": "Bullish",
      "ichimoku_cloud": "Above Cloud (Bullish)",
      "macd_histogram": 0.006957,
      "atr_pct": 0.42,
      "bb_width": 3.19,
      "oi_trend": "Stable",
      "candlestick_patterns": [
        "Doji"
      ],
      "score_signals": [
        "EMA Stack Bullish",
        "RSI 63.09 momentum zone",
        "MACD Bullish",
        "BB squeeze \u2014 breakout imminent",
        "Supertrend Bullish",
        "Above Ichimoku Cloud",
        "Williams %R overbought",
        "CCI 121.09 overbought"
      ],
      "commentary": [
        "BB squeeze detected (3.19% width) \u2014 a large move is coming but direction not yet confirmed. Wait for price to break clearly above/below the bands before entering.",
        "ADX 14.23 \u2014 Trend is weak. Price may chop rather than trend. Reduce size.",
        "Funding is deeply negative (-1.4526%/8h) \u2014 shorts are paying heavily. This is classic squeeze fuel. Any positive catalyst could trigger rapid short covering.",
        "RSI 63.09 is in the ideal momentum zone \u2014 not overbought, not oversold. Clean entry conditions.",
        "Both Ichimoku Cloud and Supertrend agree \u2014 bullish structure confirmed on multiple timeframes.",
        "\u23f3 Entry timing: WAIT \u2014 BB squeeze means direction unclear. Enter only after clear breakout candle closes."
      ],
      "warning": "",
      "quality": "RISKY",
      "risky_flags": [
        "ADX 14.23 < 20 \u2014 no trend (Wilder threshold)"
      ]
    },
    {
      "type": "MOMENTUM",
      "direction": "LONG",
      "coin": "USUAL",
      "symbol": "USUALUSD",
      "sector": "DeFi",
      "instrument": "USUAL Perpetual Futures",
      "entry": "Long USUAL near $0.009689",
      "stop_loss": "SL: $0.009477 (ATR-based -2.0%) or below $0.0094",
      "target": "T1: $0.00996 (+3.0%) | T2: $0.010153 (+5.0%) | Key resistance: $0.0102",
      "risk_reward": "R:R 1:1.5 to 1:2.5",
      "confidence": 78,
      "reasons": [
        "Strong Uptrend",
        "RSI 62.97 momentum zone",
        "MACD histogram positive",
        "Supertrend Bullish",
        "Above Ichimoku Cloud",
        "Bullish TK Cross"
      ],
      "funding_note": "Funding -3.6693%/8h (~-4018% annualized)",
      "current_price": 0.00967,
      "rsi": 62.97,
      "rsi_hourly": 47.88,
      "trend": "Strong Uptrend",
      "adx": 9.04,
      "adx_strength": "Weak",
      "supertrend": "Bullish",
      "ichimoku_cloud": "Above Cloud (Bullish)",
      "macd_histogram": 8e-06,
      "atr_pct": 0.69,
      "bb_width": 3.2,
      "oi_trend": "Stable",
      "candlestick_patterns": [],
      "score_signals": [
        "EMA Stack Bullish",
        "RSI 62.97 momentum zone",
        "MACD Bullish",
        "BB squeeze \u2014 breakout imminent",
        "Supertrend Bullish",
        "Above Ichimoku Cloud",
        "Stoch RSI bullish cross",
        "Williams %R overbought"
      ],
      "commentary": [
        "BB squeeze detected (3.2% width) \u2014 a large move is coming but direction not yet confirmed. Wait for price to break clearly above/below the bands before entering.",
        "ADX 9.04 \u2014 Trend is weak. Price may chop rather than trend. Reduce size.",
        "Funding is deeply negative (-3.6693%/8h) \u2014 shorts are paying heavily. This is classic squeeze fuel. Any positive catalyst could trigger rapid short covering.",
        "RSI 62.97 is in the ideal momentum zone \u2014 not overbought, not oversold. Clean entry conditions.",
        "Both Ichimoku Cloud and Supertrend agree \u2014 bullish structure confirmed on multiple timeframes.",
        "\u23f3 Entry timing: WAIT \u2014 BB squeeze means direction unclear. Enter only after clear breakout candle closes."
      ],
      "warning": "",
      "quality": "RISKY",
      "risky_flags": [
        "ADX 9.04 < 20 \u2014 no trend (Wilder threshold)"
      ]
    },
    {
      "type": "MOMENTUM",
      "direction": "LONG",
      "coin": "MASK",
      "symbol": "MASKUSD",
      "sector": "AI",
      "instrument": "MASK Perpetual Futures",
      "entry": "Long MASK near $0.424648",
      "stop_loss": "SL: $0.415324 (ATR-based -2.0%) or below $0.417",
      "target": "T1: $0.436514 (+3.0%) | T2: $0.44499 (+5.0%) | Key resistance: $0.4249",
      "risk_reward": "R:R 1:1.5 to 1:2.5",
      "confidence": 75,
      "reasons": [
        "Recovery \u2014 bounce in progress",
        "RSI 54.35 momentum zone",
        "MACD histogram positive",
        "Supertrend Bullish",
        "Above Ichimoku Cloud",
        "Parabolic SAR Bullish"
      ],
      "funding_note": "Funding -1.8819%/8h (~-2061% annualized)",
      "current_price": 0.4238,
      "rsi": 54.35,
      "rsi_hourly": 38.09,
      "trend": "Recovery",
      "adx": 16.72,
      "adx_strength": "Weak",
      "supertrend": "Bullish",
      "ichimoku_cloud": "Above Cloud (Bullish)",
      "macd_histogram": 0.000198,
      "atr_pct": 0.8,
      "bb_width": 2.64,
      "oi_trend": "Stable",
      "candlestick_patterns": [
        "Doji"
      ],
      "score_signals": [
        "RSI 54.35 momentum zone",
        "MACD Bullish",
        "BB squeeze \u2014 breakout imminent",
        "Supertrend Bullish",
        "Above Ichimoku Cloud",
        "Stoch RSI bullish cross",
        "Williams %R overbought",
        "OBV rising \u2014 buying pressure"
      ],
      "commentary": [
        "BB squeeze detected (2.64% width) \u2014 a large move is coming but direction not yet confirmed. Wait for price to break clearly above/below the bands before entering.",
        "ADX 16.72 \u2014 Trend is weak. Price may chop rather than trend. Reduce size.",
        "Funding is deeply negative (-1.8819%/8h) \u2014 shorts are paying heavily. This is classic squeeze fuel. Any positive catalyst could trigger rapid short covering.",
        "RSI 54.35 is in the ideal momentum zone \u2014 not overbought, not oversold. Clean entry conditions.",
        "Both Ichimoku Cloud and Supertrend agree \u2014 bullish structure confirmed on multiple timeframes.",
        "\u23f3 Entry timing: WAIT \u2014 BB squeeze means direction unclear. Enter only after clear breakout candle closes."
      ],
      "warning": "",
      "quality": "RISKY",
      "risky_flags": [
        "ADX 16.72 < 20 \u2014 no trend (Wilder threshold)"
      ]
    },
    {
      "type": "MOMENTUM",
      "direction": "LONG",
      "coin": "CAKE",
      "symbol": "CAKEUSD",
      "sector": "DeFi",
      "instrument": "CAKE Perpetual Futures",
      "entry": "Long CAKE near $1.394984",
      "stop_loss": "SL: $1.364356 (ATR-based -2.0%) or below $1.3901",
      "target": "T1: $1.433966 (+3.0%) | T2: $1.46181 (+5.0%) | Key resistance: $1.4026",
      "risk_reward": "R:R 1:1.5 to 1:2.5",
      "confidence": 70,
      "reasons": [
        "Recovery \u2014 bounce in progress",
        "RSI 53.27 momentum zone",
        "MACD histogram positive",
        "Supertrend Bullish",
        "Bullish TK Cross",
        "Parabolic SAR Bullish"
      ],
      "funding_note": "Funding -1.8406%/8h (~-2015% annualized)",
      "current_price": 1.3922,
      "rsi": 53.27,
      "rsi_hourly": 43.74,
      "trend": "Recovery",
      "adx": 12.63,
      "adx_strength": "Weak",
      "supertrend": "Bullish",
      "ichimoku_cloud": "Below Cloud (Bearish)",
      "macd_histogram": 0.001802,
      "atr_pct": 0.38,
      "bb_width": 2.31,
      "oi_trend": "Stable",
      "candlestick_patterns": [],
      "score_signals": [
        "RSI 53.27 momentum zone",
        "MACD Bullish",
        "BB squeeze \u2014 breakout imminent",
        "Supertrend Bullish",
        "Below Ichimoku Cloud",
        "Stoch RSI bullish cross",
        "OBV falling \u2014 selling pressure",
        "Parabolic SAR Bullish"
      ],
      "commentary": [
        "\u26a0\ufe0f Conflicting signals detected:",
        "  \u2192 Supertrend bullish but price is below Ichimoku Cloud \u2014 mixed structure",
        "BB squeeze detected (2.31% width) \u2014 a large move is coming but direction not yet confirmed. Wait for price to break clearly above/below the bands before entering.",
        "ADX 12.63 \u2014 Trend is weak. Price may chop rather than trend. Reduce size.",
        "Funding is deeply negative (-1.8406%/8h) \u2014 shorts are paying heavily. This is classic squeeze fuel. Any positive catalyst could trigger rapid short covering.",
        "RSI 53.27 is in the ideal momentum zone \u2014 not overbought, not oversold. Clean entry conditions.",
        "\u23f3 Entry timing: WAIT \u2014 BB squeeze means direction unclear. Enter only after clear breakout candle closes."
      ],
      "warning": "",
      "quality": "RISKY",
      "risky_flags": [
        "ADX 12.63 < 20 \u2014 no trend (Wilder threshold)"
      ]
    }
  ],
  "clean_count": 9,
  "risky_count": 37,
  "astro_summary": {
    "moon_phase": "Last Quarter",
    "moon_bias": "bearish",
    "day_ruler": "Mercury",
    "astro_score": 47,
    "retrograde_planets": [
      "Mercury",
      "Rahu",
      "Ketu"
    ]
  }
}